visual_graph_datasets/VERSION
visual_graph_datasets/__init__.py
visual_graph_datasets/cli.py
visual_graph_datasets/config.py
visual_graph_datasets/data.py
visual_graph_datasets/graph.py
visual_graph_datasets/models.py
visual_graph_datasets/testing.py
visual_graph_datasets/typing.py
visual_graph_datasets/util.py
visual_graph_datasets/web.py
visual_graph_datasets/examples/00_quickstart.py
visual_graph_datasets/examples/01_explanation_pdf.py
visual_graph_datasets/examples/README.rst
visual_graph_datasets/examples/__init__.py
visual_graph_datasets/experiments/README.rst
visual_graph_datasets/experiments/analyze_color_graph_dataset.py
visual_graph_datasets/experiments/analyze_color_graph_dataset__rgb_dual_motifs.py
visual_graph_datasets/experiments/csv_ames_mutagenicity.py
visual_graph_datasets/experiments/csv_gao_bbbp_dataset.py
visual_graph_datasets/experiments/csv_pereira_dipole_moment.py
visual_graph_datasets/experiments/csv_sanchez_lengeling_dataset.py
visual_graph_datasets/experiments/generate_mock.py
visual_graph_datasets/experiments/generate_molecule_dataset_from_csv.py
visual_graph_datasets/experiments/generate_molecule_dataset_from_csv__aggregators_binary.py
visual_graph_datasets/experiments/generate_molecule_dataset_from_csv__aggregators_binary_protonated.py
visual_graph_datasets/experiments/generate_molecule_dataset_from_csv__aggregators_lee.py
visual_graph_datasets/experiments/generate_molecule_dataset_from_csv__ampc_combined.py
visual_graph_datasets/experiments/generate_molecule_dataset_from_csv__aqsoldb.py
visual_graph_datasets/experiments/generate_molecule_dataset_from_csv__bbbp.py
visual_graph_datasets/experiments/generate_molecule_dataset_from_csv__binary_global.py
visual_graph_datasets/experiments/generate_molecule_dataset_from_csv__binary_local.py
visual_graph_datasets/experiments/generate_molecule_dataset_from_csv__compas.py
visual_graph_datasets/experiments/generate_molecule_dataset_from_csv__dipole_moment.py
visual_graph_datasets-0.17.0.dist-info/METADATA
visual_graph_datasets-0.17.0.dist-info/WHEEL
visual_graph_datasets-0.17.0.dist-info/entry_points.txt
visual_graph_datasets-0.17.0.dist-info/RECORD
