Metadata-Version: 2.4
Name: visual_graph_datasets
Version: 0.17.0
Summary: Datasets for the training of graph neural networks (GNNs) and subsequent visualization of attributional explanations of XAI methods
Author-email: Jonas Teufel <jonseb1998@gmail.com>
Maintainer-email: Jonas Teufel <jonseb1998@gmail.com>
License: MIT License
Keywords: GNN,XAI,datasets,explainable AI,graph neural networks,machine learning,molecular,networkx,rdkit,visualization
Classifier: Development Status :: 4 - Beta
Classifier: Intended Audience :: Developers
Classifier: Intended Audience :: Science/Research
Classifier: License :: OSI Approved :: MIT License
Classifier: Operating System :: OS Independent
Classifier: Programming Language :: Python :: 3
Classifier: Programming Language :: Python :: 3.8
Classifier: Programming Language :: Python :: 3.9
Classifier: Programming Language :: Python :: 3.10
Classifier: Programming Language :: Python :: 3.11
Classifier: Programming Language :: Python :: 3.12
Classifier: Programming Language :: Python :: 3.13
Classifier: Programming Language :: Python :: 3.14
Classifier: Topic :: Scientific/Engineering :: Artificial Intelligence
Classifier: Topic :: Scientific/Engineering :: Visualization
Classifier: Topic :: Software Development :: Libraries :: Python Modules
Requires-Python: <=3.14,>=3.8
Requires-Dist: cairosvg>=2.5.0
Requires-Dist: imageio>=2.22.4
Requires-Dist: jinja2>=3.0.3
Requires-Dist: matplotlib>=3.5.3
Requires-Dist: networkx>=2.8.8
Requires-Dist: numpy<2.0.0,>=1.22.0
Requires-Dist: orjson>=3.8.0
Requires-Dist: parsimonious>=0.10.0
Requires-Dist: poetry-bumpversion>=0.3.0
Requires-Dist: psutil>=5.7.2
Requires-Dist: pycomex>=0.14.0
Requires-Dist: pytest>=7.2.0
Requires-Dist: pyyaml>=0.6.0
Requires-Dist: rdkit>=2022.9.0
Requires-Dist: rich-click>=1.8.3
Requires-Dist: scipy>=1.10.1
